coolpuppy/CLI.py
coolpuppy/__init__.py
coolpuppy/_version.py
coolpuppy/coolpup.py
coolpuppy/divide_pups_CLI.py
coolpuppy/plotpup.py
coolpuppy/plotpuppy_CLI.py
coolpuppy/lib/__init__.py
coolpuppy/lib/io.py
coolpuppy/lib/numutils.py
coolpuppy/lib/puputils.py
coolpuppy/lib/util.py
coolpuppy-1.1.0.dist-info/LICENSE
coolpuppy-1.1.0.dist-info/METADATA
coolpuppy-1.1.0.dist-info/WHEEL
coolpuppy-1.1.0.dist-info/entry_points.txt
coolpuppy-1.1.0.dist-info/top_level.txt
coolpuppy-1.1.0.dist-info/RECORD
