Metadata-Version: 2.1
Name: coolpuppy
Version: 1.1.0
Summary: A versatile tool to perform pile-up analysis on Hi-C data in .cool format.
Author: Open2C
Author-email: flyamer@gmail.com
Project-URL: Source, https://github.com/open2c/coolpuppy
Project-URL: Issues, https://github.com/open2c/coolpuppy/issues
Classifier: Programming Language :: Python
Classifier: Programming Language :: Python :: 3
Classifier: Programming Language :: Python :: 3.8
Classifier: Programming Language :: Python :: 3.9
Classifier: Programming Language :: Python :: 3.10
Classifier: License :: OSI Approved :: MIT License
Classifier: Operating System :: OS Independent
Requires-Python: >=3.8
License-File: LICENSE
Requires-Dist: h5py (>=3.0)
Requires-Dist: Cython
Requires-Dist: cooler
Requires-Dist: numpy (>=1.16.5)
Requires-Dist: pandas
Requires-Dist: scipy
Requires-Dist: cooltools (>=0.5.2)
Requires-Dist: pyyaml
Requires-Dist: more-itertools
Requires-Dist: bioframe (>=0.3.3)
Requires-Dist: matplotlib
Requires-Dist: seaborn
Requires-Dist: natsort
Requires-Dist: m2r2
Requires-Dist: h5sparse
Requires-Dist: multiprocessing-logging
